bolt_lab/__init__.py
bolt_lab/cli_gcd.py
bolt_lab/cli_openset.py
bolt_lab/paths.py
bolt_lab/run_grid.py
bolt_lab/utils.py
bolt_lab/workspace.py
bolt_lab/code/gcd/baselines/ALUP/README.md
bolt_lab/code/gcd/baselines/ALUP/run.py
bolt_lab/code/gcd/baselines/ALUP/utils.py
bolt_lab/code/gcd/baselines/ALUP/__pycache__/run.cpython-310.pyc
bolt_lab/code/gcd/baselines/ALUP/__pycache__/utils.cpython-310.pyc
bolt_lab/code/gcd/baselines/ALUP/__pycache__/utils.cpython-312.pyc
bolt_lab/code/gcd/baselines/ALUP/dataloaders/base_data.py
bolt_lab/code/gcd/baselines/ALUP/dataloaders/__pycache__/base_data.cpython-310.pyc
bolt_lab/code/gcd/baselines/ALUP/dataloaders/__pycache__/base_data.cpython-312.pyc
bolt_lab/code/gcd/baselines/ALUP/losses/contrastive_loss.py
bolt_lab/code/gcd/baselines/ALUP/losses/__pycache__/contrastive_loss.cpython-310.pyc
bolt_lab/code/gcd/baselines/ALUP/losses/__pycache__/contrastive_loss.cpython-312.pyc
bolt_lab/code/gcd/baselines/ALUP/methods/alup/al_manager.py
bolt_lab/code/gcd/baselines/ALUP/methods/alup/build_prompt.py
bolt_lab/code/gcd/baselines/ALUP/methods/alup/manager.py
bolt_lab/code/gcd/baselines/ALUP/methods/alup/model.py
bolt_lab/code/gcd/baselines/ALUP/methods/alup/pretrain_manager.py
bolt_lab/code/gcd/baselines/ALUP/methods/alup/utils_LLM.py
bolt_lab/code/gcd/baselines/ALUP/methods/alup/utils_data.py
bolt_lab/code/gcd/baselines/ALUP/methods/alup/utils_prompt.py
bolt_lab/code/gcd/baselines/ALUP/methods/alup/__pycache__/al_manager.cpython-310.pyc
bolt_lab/code/gcd/baselines/ALUP/methods/alup/__pycache__/build_prompt.cpython-310.pyc
bolt_lab/code/gcd/baselines/ALUP/methods/alup/__pycache__/manager.cpython-310.pyc
bolt_lab/code/gcd/baselines/ALUP/methods/alup/__pycache__/manager.cpython-312.pyc
bolt_lab/code/gcd/baselines/ALUP/methods/alup/__pycache__/model.cpython-310.pyc
bolt_lab/code/gcd/baselines/ALUP/methods/alup/__pycache__/model.cpython-312.pyc
bolt_lab/code/gcd/baselines/ALUP/methods/alup/__pycache__/pretrain_manager.cpython-310.pyc
bolt_lab-0.1.1.dist-info/METADATA
bolt_lab-0.1.1.dist-info/WHEEL
bolt_lab-0.1.1.dist-info/entry_points.txt
bolt_lab-0.1.1.dist-info/top_level.txt
bolt_lab-0.1.1.dist-info/RECORD
