Metadata-Version: 2.4
Name: bolt-lab
Version: 0.1.1
Summary: Bolt research project (packaged) with stable paths and workspace execution
License: MIT
Requires-Python: >=3.9
Requires-Dist: pyyaml>=6.0
Requires-Dist: numpy>=1.23
Requires-Dist: pandas>=2.0
Provides-Extra: hf
Requires-Dist: huggingface_hub>=0.20; extra == "hf"
Requires-Dist: transformers>=4.35; extra == "hf"
Requires-Dist: datasets>=2.16; extra == "hf"
